Assignment7_pkg/__init__.py
Assignment7_pkg/avg_purchase_frq_by_state.py
Assignment7_pkg/orders_total_amt.py
Assignment7_pkg-0.1.dist-info/Licence.txt
Assignment7_pkg-0.1.dist-info/METADATA
Assignment7_pkg-0.1.dist-info/WHEEL
Assignment7_pkg-0.1.dist-info/top_level.txt
Assignment7_pkg-0.1.dist-info/RECORD
